lemon_tizer/__init__.py
lemon_tizer/main.py
lemon_tizer-0.0.7.dist-info/METADATA
lemon_tizer-0.0.7.dist-info/WHEEL
lemon_tizer-0.0.7.dist-info/licenses/LICENSE
lemon_tizer-0.0.7.dist-info/RECORD
