Metadata-Version: 2.3
Name: lemon_tizer
Version: 0.0.7
Summary: LemonTizer is a class that wraps the spacy library to build a lemmatizer for language learning applications.
Project-URL: Homepage, https://github.com/jonathanfox5/lemon_tizer
Project-URL: Issues, https://github.com/jonathanfox5/lemon_tizer/issues
Author: Jonathan Fox
License: MIT License
Keywords: lemmatizer,spacy,wrapper
Classifier: License :: OSI Approved :: MIT License
Classifier: Operating System :: OS Independent
Classifier: Programming Language :: Python :: 3
Requires-Python: >=3.10
Requires-Dist: spacy
